hi.v
`timescale 1ns/1ps

module FF_T(Q, T, clk, rst);
    input T, clk, rst;
    output reg Q;

    always @ (posedge clk or negedge rst)
        if (!rst)         
            Q <= 0;
        else if (T)
            Q <= ~Q;
        else
            Q <= Q;  
endmodule

module ex1(A,B,C,D,Y,reset,clock);
    output A,B,C,D;
    input Y, clock, reset;
    wire TA, TB, TC, TD;

    assign TA = ((~B) & (~C) & (~Y)) | (B & C & Y);
    assign TB = ((~C) & (~Y)) | (C & Y);
    assign TC = 1;
    assign TD = 0;

    FF_T FF_A(A,TA,clock, reset);
    FF_T FF_B(B,TB,clock, reset);
    FF_T FF_C(C,TC,clock, reset);
    FF_T FF_D(D,TD,clock, reset);

endmodule

hi_tb.v
`timescale 1ns / 1ps

module ex1_tb();
    wire [3:0] t_Q;
    reg t_Y, t_clk, t_reset;

    ex1 dut(t_Q[3], t_Q[2], t_Q[1], t_Q[0], t_Y, t_reset, t_clk);

    initial begin 
        t_clk = 1'b0;
        forever #5 t_clk = ~t_clk;
    end

    initial 
        begin
            t_reset = 1'b0;  
            #10 t_reset = 1'b1; 
        end

    initial begin
        t_Y = 1'b1;
        #30 t_Y = 1'b0;
        #70 t_Y = 1'b1;
    end

    initial #130 $finish;

    initial begin
        $display("Program by Jed Julian");
        $monitor("time=%03d, Clk=%b, reset=%b, Y=%b, state=%b%b%b%b", 
                  $time, t_clk, t_reset, t_Y, t_Q[3], t_Q[2], t_Q[1], t_Q[0]);
        $dumpfile("jed_julian.vcd"); 
        $dumpvars(0, ex1_tb);        
    end

endmodule

jed_julian.vcd
$date
	Sun Apr 06 21:44:04 2025
$end
$version
	Icarus Verilog
$end
$timescale
	1ps
$end
$scope module ex1_tb $end
$var wire 4 ! t_Q [3:0] $end
$var reg 1 " t_Y $end
$var reg 1 # t_clk $end
$var reg 1 $ t_reset $end
$scope module dut $end
$var wire 1 % TA $end
$var wire 1 & TB $end
$var wire 1 ' TC $end
$var wire 1 ( TD $end
$var wire 1 " Y $end
$var wire 1 # clock $end
$var wire 1 $ reset $end
$var wire 1 ) D $end
$var wire 1 * C $end
$var wire 1 + B $end
$var wire 1 , A $end
$scope module FF_A $end
$var wire 1 % T $end
$var wire 1 # clk $end
$var wire 1 $ rst $end
$var reg 1 , Q $end
$upscope $end
$scope module FF_B $end
$var wire 1 & T $end
$var wire 1 # clk $end
$var wire 1 $ rst $end
$var reg 1 + Q $end
$upscope $end
$scope module FF_C $end
$var wire 1 ' T $end
$var wire 1 # clk $end
$var wire 1 $ rst $end
$var reg 1 * Q $end
$upscope $end
$scope module FF_D $end
$var wire 1 ( T $end
$var wire 1 # clk $end
$var wire 1 $ rst $end
$var reg 1 ) Q $end
$upscope $end
$upscope $end
$upscope $end
$enddefinitions $end
$comment Show the parameter values. $end
$dumpall
$end
#0
$dumpvars
0,
0+
0*
0)
0(
1'
0&
0%
0$
0#
1"
b0 !
$end
#5000
1#
#10000
0#
1$
#15000
1&
b10 !
1*
1#
#20000
0#
#25000
0&
0*
b100 !
1+
1#
#30000
1&
0#
0"
#35000
0&
0+
b10 !
1*
1#
#40000
0#
#45000
1%
1&
b0 !
0*
1#
#50000
0#
#55000
0%
0&
1,
1+
b1110 !
1*
1#
#60000
0#
#65000
1&
b1100 !
0*
1#
#70000
0#
#75000
0&
0+
b1010 !
1*
1#
#80000
0#
#85000
1%
1&
b1000 !
0*
1#
#90000
0#
#95000
0%
0&
0,
1+
b110 !
1*
1#
#100000
1%
1&
0#
1"
#105000
0%
0&
0*
0+
b1000 !
1,
1#
#110000
0#
#115000
1&
b1010 !
1*
1#
#120000
0#
#125000
0&
0*
b1100 !
1+
1#
