hi.v
`timescale 1ns/1ps

module FF_T(Q, T, clk, rst);
    input T, clk, rst;
    output reg Q;

    always @ (posedge clk or negedge rst)
        if (!rst)
            Q <= 1'b0;           // ✅ initialize to 0 on reset
        else if (T == 1'b1)
            Q <= ~Q;             // ✅ toggle if T = 1
        else
            Q <= Q;              // ✅ retain value if T = 0
endmodule

module ex1(A,B,C,D,Y,reset, clock);
    output A,B,C,D;
    input Y, reset, clock;
    wire TA, TB, TC, TD;
    wire QA,QB,QC,QD;

    assign TA = QC&QD;
    assign TB = QD;
    assign TC = 1'b1;
    assign TD = 1'b0;

    FF_T F1(QA, TA, clock, reset);
    FF_T F2(QB, TB, clock, reset);
    FF_T F3(QC, TC, clock, reset);
    FF_T F4(QD, TD, clock, reset);

    assign A = QA;
    assign B = QB;
    assign C = QC;
    assign D = QD;
endmodule

hi_tb.v
`timescale 1ns / 1ps

module ex1_tb();
    wire A, B, C, D;
    reg t_Y, t_clk, t_reset;

    // Instantiate your design with correct signal names
    ex1 dut(A, B, C, D, t_Y, t_reset, t_clk);

    // Clock generation: 10 ns period
    initial begin 
        t_clk = 1'b0;
        forever #5 t_clk = ~t_clk;
    end

    // Reset logic
    initial begin
        t_reset = 1'b0;   // Active low reset
        #10 t_reset = 1'b1; // Release reset after 10ns
    end

    // Input Y toggle logic
    initial begin
        t_Y = 1'b1;
        #70 t_Y = 1'b0;
        #30 t_Y = 1'b1;
    end

    // End simulation after 130 ns
    initial #130 $finish;

    // Display and dump signals
    initial begin
        $display("Program by Jed Julian");
        $monitor("time=%03d, Clk=%b, reset=%b, Y=%b, state=%b%b%b%b", 
                  $time, t_clk, t_reset, t_Y, A, B, C, D);
        $dumpfile("jed_julian.vcd"); // ✅ must end with .vcd
        $dumpvars(0, ex1_tb);        // ✅ dump all variables in this module
    end

endmodule

jed_julian.vcd
$date
	Sun Apr 06 03:39:02 2025
$end
$version
	Icarus Verilog
$end
$timescale
	1ps
$end
$scope module ex1_tb $end
$var wire 1 ! D $end
$var wire 1 " C $end
$var wire 1 # B $end
$var wire 1 $ A $end
$var reg 1 % t_Y $end
$var reg 1 & t_clk $end
$var reg 1 ' t_reset $end
$scope module dut $end
$var wire 1 $ A $end
$var wire 1 # B $end
$var wire 1 " C $end
$var wire 1 ! D $end
$var wire 1 ( TA $end
$var wire 1 ) TB $end
$var wire 1 * TC $end
$var wire 1 + TD $end
$var wire 1 % Y $end
$var wire 1 & clock $end
$var wire 1 ' reset $end
$var wire 1 , QD $end
$var wire 1 - QC $end
$var wire 1 . QB $end
$var wire 1 / QA $end
$scope module F1 $end
$var wire 1 ( T $end
$var wire 1 & clk $end
$var wire 1 ' rst $end
$var reg 1 / Q $end
$upscope $end
$scope module F2 $end
$var wire 1 ) T $end
$var wire 1 & clk $end
$var wire 1 ' rst $end
$var reg 1 . Q $end
$upscope $end
$scope module F3 $end
$var wire 1 * T $end
$var wire 1 & clk $end
$var wire 1 ' rst $end
$var reg 1 - Q $end
$upscope $end
$scope module F4 $end
$var wire 1 + T $end
$var wire 1 & clk $end
$var wire 1 ' rst $end
$var reg 1 , Q $end
$upscope $end
$upscope $end
$upscope $end
$enddefinitions $end
$comment Show the parameter values. $end
$dumpall
$end
#0
$dumpvars
0/
0.
0-
0,
0+
1*
0)
0(
0'
0&
1%
0$
0#
0"
0!
$end
#5000
1&
#10000
0&
1'
#15000
1"
1-
1&
#20000
0&
#25000
0"
0-
1&
#30000
0&
#35000
1"
1-
1&
#40000
0&
#45000
0"
0-
1&
#50000
0&
#55000
1"
1-
1&
#60000
0&
#65000
0"
0-
1&
#70000
0&
0%
#75000
1"
1-
1&
#80000
0&
#85000
0"
0-
1&
#90000
0&
#95000
1"
1-
1&
#100000
0&
1%
#105000
0"
0-
1&
#110000
0&
#115000
1"
1-
1&
#120000
0&
#125000
0"
0-
1&
